lyipc/__init__.py
lyipc/interpreter.py
lyipc/server.py
lyipc/start_server.lym
lyipc/client/__init__.py
lyipc/client/command_line.py
lyipc/client/dependent.py
lyipc/client/general.py
lyipc/client/phidl.py
lyipc/client/pya.py
lyipc/client/remotehost.py
lyipc-0.2.14.dist-info/LICENSE
lyipc-0.2.14.dist-info/METADATA
lyipc-0.2.14.dist-info/WHEEL
lyipc-0.2.14.dist-info/entry_points.txt
lyipc-0.2.14.dist-info/top_level.txt
lyipc-0.2.14.dist-info/RECORD
