Metadata-Version: 2.1
Name: lyipc
Version: 0.2.14
Summary: Inter-process communication for Klayout
Home-page: https://github.com/atait/klayout-ipc
Author: Alex Tait
Author-email: alexander.tait@nist.gov
License: MIT
License-File: LICENSE
Requires-Dist: lygadgets >=0.1.19
